scripts/__init__.py
semviqa/__init__.py
semviqa/pipeline.py
semviqa/data_processing/__init__.py
semviqa/data_processing/pipline.py
semviqa/ser/__init__.py
semviqa/ser/data_utils.py
semviqa/ser/loss.py
semviqa/ser/main.py
semviqa/ser/main_ds.py
semviqa/ser/qatc_model.py
semviqa/ser/ser_eval.py
semviqa/ser/utils.py
semviqa/tvc/__init__.py
semviqa/tvc/data_utils.py
semviqa/tvc/loss.py
semviqa/tvc/main.py
semviqa/tvc/main_ds.py
semviqa/tvc/model.py
semviqa/tvc/tvc_eval.py
semviqa-1.1.10.dist-info/licenses/LICENSE.txt
semviqa-1.1.10.dist-info/METADATA
semviqa-1.1.10.dist-info/WHEEL
semviqa-1.1.10.dist-info/top_level.txt
semviqa-1.1.10.dist-info/RECORD
