Metadata-Version: 2.4
Name: semviqa
Version: 1.1.10
Summary: SemViQA: A Semantic Question Answering System for Vietnamese Fact-Checking
Home-page: https://github.com/DAVID-NGUYEN-S16/SemViQA
Author: Dien X. Tran, Nam V. Nguyen, Thanh T. Tran, Anh T. Hoang, Tai V. Duong, Di T. Le, Phuc-Lu Le
Author-email: xuandienk4@gmail.com
Project-URL: Paper, https://arxiv.org/abs/2503.00955
Project-URL: Repository, https://github.com/DAVID-NGUYEN-S16/SemViQA
Project-URL: Competition Results, https://codalab.lisn.upsaclay.fr/competitions/15497#results
Keywords: Vietnamese NLP,Fact-Checking,Question Answering,Machine Learning
Classifier: Programming Language :: Python :: 3
Classifier: License :: OSI Approved :: MIT License
Classifier: Operating System :: OS Independent
Classifier: Topic :: Scientific/Engineering :: Artificial Intelligence
Classifier: Intended Audience :: Developers
Requires-Python: >=3.8
License-File: LICENSE.txt
Requires-Dist: transformers==4.42.3
Requires-Dist: datasets==2.20.0
Requires-Dist: pandas==2.2.2
Requires-Dist: numpy==1.26.4
Requires-Dist: underthesea==6.8.4
Requires-Dist: gc-python-utils==0.0.1
Requires-Dist: tqdm==4.66.4
Requires-Dist: safetensors==0.4.3
Requires-Dist: sentence-transformers==3.0.1
Requires-Dist: scikit-learn==1.2.2
Requires-Dist: matplotlib==3.7.5
Requires-Dist: accelerate==0.32.1
Requires-Dist: omegaconf==2.3.0
Requires-Dist: einops==0.8.0
Requires-Dist: rank_bm25==0.2.2
Requires-Dist: sentencepiece==0.2.0
Requires-Dist: pyvi==0.1.1
Requires-Dist: deepspeed==0.17.1
Dynamic: author
Dynamic: author-email
Dynamic: classifier
Dynamic: description
Dynamic: description-content-type
Dynamic: home-page
Dynamic: keywords
Dynamic: license-file
Dynamic: project-url
Dynamic: requires-dist
Dynamic: requires-python
Dynamic: summary
